django_sft/__init__.py
django_sft/apps.py
django_sft/compiler.py
django_sft/parser.py
django_sft/settings.py
django_sft/template.py
django_sft/management/commands/compile_sft.py
django_sft/test_utils/__init__.py
django_sft/test_utils/test_app/__init__.py
django_sft/test_utils/test_app/admin.py
django_sft/test_utils/test_app/apps.py
django_sft/test_utils/test_app/models.py
django_sft/test_utils/test_app/migrations/__init__.py
django_sft-0.1.2.dist-info/AUTHORS.rst
django_sft-0.1.2.dist-info/LICENSE
django_sft-0.1.2.dist-info/METADATA
django_sft-0.1.2.dist-info/WHEEL
django_sft-0.1.2.dist-info/top_level.txt
django_sft-0.1.2.dist-info/RECORD
