Metadata-Version: 2.1
Name: django-sft
Version: 0.1.2
Summary: Django Single File Templates -- inspired by Vue's Single file components
Home-page: https://github.com/zanderle/django-sft
Author: Zan Anderle
Author-email: hello@zanderle.com
License: MIT
Keywords: django-sft
Platform: UNKNOWN
Classifier: Development Status :: 3 - Alpha
Classifier: Framework :: Django :: 1.11
Classifier: Framework :: Django :: 2.1
Classifier: Framework :: Django :: 3.1
Classifier: Intended Audience :: Developers
Classifier: License :: OSI Approved :: BSD License
Classifier: Natural Language :: English
Classifier: Programming Language :: Python :: 3.9
Classifier: Programming Language :: Python :: 3.8
Classifier: Programming Language :: Python :: 3.7
Classifier: Programming Language :: Python :: 3.6
Classifier: Programming Language :: Python :: 3.5
Classifier: Programming Language :: Python :: 3
